tensiometer/__init__.py
tensiometer/chains_convergence.py
tensiometer/gaussian_tension.py
tensiometer/interfaces/__init__.py
tensiometer/interfaces/cosmosis_interface.py
tensiometer/mcmc_tension/__init__.py
tensiometer/mcmc_tension/flow.py
tensiometer/mcmc_tension/kde.py
tensiometer/mcmc_tension/param_diff.py
tensiometer/synthetic_probability/__init__.py
tensiometer/synthetic_probability/analytic_flow.py
tensiometer/synthetic_probability/fixed_bijectors.py
tensiometer/synthetic_probability/flow_CPCA.py
tensiometer/synthetic_probability/flow_profiler.py
tensiometer/synthetic_probability/flow_utilities.py
tensiometer/synthetic_probability/loss_functions.py
tensiometer/synthetic_probability/lr_schedulers.py
tensiometer/synthetic_probability/synthetic_probability.py
tensiometer/synthetic_probability/trainable_bijectors.py
tensiometer/tests/chains_convergence_test.py
tensiometer/tests/gaussian_tension_test.py
tensiometer/tests/interfaces_cosmosis_interface_test.py
tensiometer/tests/mcmc_tension_flow_test.py
tensiometer/tests/mcmc_tension_kde_test.py
tensiometer/tests/mcmc_tension_param_diff_test.py
tensiometer/tests/synthetic_probability_analytic_flow_test.py
tensiometer/tests/synthetic_probability_fixed_bijectors_additional_test.py
tensiometer/tests/synthetic_probability_flow_CPCA_test.py
tensiometer/tests/synthetic_probability_flow_profiler_unit_test.py
tensiometer/tests/synthetic_probability_flow_utilities_test.py
tensiometer/tests/synthetic_probability_loss_functions_test.py
tensiometer/tests/synthetic_probability_lr_schedulers_test.py
tensiometer/tests/synthetic_probability_test.py
tensiometer/tests/synthetic_probability_trainable_bijectors_test.py
tensiometer/tests/utilities_caching_test.py
tensiometer/tests/utilities_color_test.py
tensiometer/tests/utilities_stats_utilities_test.py
tensiometer/tests/utilities_subprocess_runner_test.py
tensiometer/tests/utilities_tensor_eigenvalues_test.py
tensiometer/utilities/__init__.py
tensiometer/utilities/caching.py
tensiometer-1.1.0.dist-info/licenses/LICENSE
tensiometer-1.1.0.dist-info/METADATA
tensiometer-1.1.0.dist-info/WHEEL
tensiometer-1.1.0.dist-info/top_level.txt
tensiometer-1.1.0.dist-info/RECORD
