Metadata-Version: 2.4
Name: tensiometer
Version: 1.1.0
Summary: Tension tools for posterior distributions
Author: Marco Raveri
License: Tensiometer
Project-URL: Source, https://github.com/mraveri/tensiometer
Project-URL: Tracker, https://github.com/mraveri/tensiometer/issues
Project-URL: Reference, https://arxiv.org/abs/1806.04649
Project-URL: Licensing, https://raw.githubusercontent.com/mraveri/tensiometer/master/LICENSE
Project-URL: Documentation, https://tensiometer.readthedocs.io
Keywords: MCMC,cosmology,statistics
Classifier: Development Status :: 4 - Beta
Classifier: Operating System :: OS Independent
Classifier: Intended Audience :: Science/Research
Classifier: Programming Language :: Python :: 3
Classifier: Programming Language :: Python :: 3.7
Classifier: Programming Language :: Python :: 3.8
Classifier: License :: OSI Approved :: GNU General Public License v3 (GPLv3)
Requires-Python: >=3.7
License-File: LICENSE
Requires-Dist: tqdm
Requires-Dist: joblib
Requires-Dist: coverage
Requires-Dist: matplotlib
Requires-Dist: psutil
Requires-Dist: numpy
Requires-Dist: scipy
Requires-Dist: sphinx
Requires-Dist: sphinxcontrib-jquery
Requires-Dist: sphinx-rtd-theme
Requires-Dist: GetDist
Requires-Dist: autograd
Requires-Dist: pymanopt==0.2.5
Requires-Dist: gast==0.4.0
Requires-Dist: numba>=0.53.0
Requires-Dist: numdifftools
Requires-Dist: tensorflow>=2.16.0
Requires-Dist: tensorflow_probability>=0.24.0
Requires-Dist: mpi4py
Requires-Dist: IPython
Provides-Extra: docs
Requires-Dist: sphinx; extra == "docs"
Requires-Dist: sphinxcontrib-jquery; extra == "docs"
Requires-Dist: sphinx-rtd-theme; extra == "docs"
Provides-Extra: dev
Requires-Dist: pytest; extra == "dev"
Requires-Dist: pytest-cov; extra == "dev"
Requires-Dist: build; extra == "dev"
Requires-Dist: twine; extra == "dev"
Requires-Dist: sphinx; extra == "dev"
Requires-Dist: sphinxcontrib-jquery; extra == "dev"
Requires-Dist: sphinx-rtd-theme; extra == "dev"
Dynamic: license-file
